map_object/__init__.py
map_object-1.1.1.dist-info/DESCRIPTION.rst
map_object-1.1.1.dist-info/METADATA
map_object-1.1.1.dist-info/RECORD
map_object-1.1.1.dist-info/WHEEL
map_object-1.1.1.dist-info/metadata.json
map_object-1.1.1.dist-info/top_level.txt
src/__init__.py
